SIC_Assembler/main.py
assembler0928-0.0.1.dist-info/METADATA
assembler0928-0.0.1.dist-info/WHEEL
assembler0928-0.0.1.dist-info/top_level.txt
assembler0928-0.0.1.dist-info/RECORD
