Metadata-Version: 2.1
Name: assembler0928
Version: 0.0.1
Summary: QQ
Home-page: https://github.com/Qing0928/SIC_Assembler
Author: Qing
Author-email: rs040215@gmail.com
License: UNKNOWN
Platform: UNKNOWN
